tla2528/__init__.py
tla2528/enums.py
tla2528/exceptions.py
tla2528/registers.py
tla2528/tla2528.py
tla2528-0.1.0.dist-info/licenses/LICENSE
tla2528-0.1.0.dist-info/METADATA
tla2528-0.1.0.dist-info/WHEEL
tla2528-0.1.0.dist-info/top_level.txt
tla2528-0.1.0.dist-info/RECORD
