Metadata-Version: 2.4
Name: tla2528
Version: 0.1.0
Summary: Python library for TLA2528 ADC on Raspberry Pi and Linux
Author: ElectroNick_co
License: MIT
Project-URL: Homepage, https://github.com/electronick-co/tla2528-raspberry
Project-URL: Documentation, https://github.com/electronick-co/tla2528-raspberry#readme
Project-URL: Repository, https://github.com/electronick-co/tla2528-raspberry
Project-URL: Bug Tracker, https://github.com/electronick-co/tla2528-raspberry/issues
Keywords: tla2528,adc,i2c,raspberry-pi,sensor,analog
Classifier: Development Status :: 3 - Alpha
Classifier: Intended Audience :: Developers
Classifier: Programming Language :: Python :: 3
Classifier: Programming Language :: Python :: 3.8
Classifier: Programming Language :: Python :: 3.9
Classifier: Programming Language :: Python :: 3.10
Classifier: Programming Language :: Python :: 3.11
Classifier: Programming Language :: Python :: 3.12
Classifier: Topic :: Software Development :: Libraries :: Python Modules
Classifier: Topic :: System :: Hardware
Requires-Python: >=3.8
License-File: LICENSE
Requires-Dist: smbus2>=0.4.0
Provides-Extra: dev
Requires-Dist: pytest>=7.0; extra == "dev"
Requires-Dist: pytest-cov>=3.0; extra == "dev"
Requires-Dist: black>=22.0; extra == "dev"
Requires-Dist: flake8>=4.0; extra == "dev"
Requires-Dist: mypy>=0.950; extra == "dev"
Dynamic: license-file
